scMDCF/__init__.py
scMDCF/layer.py
scMDCF/train.py
scMDCF/utils.py
scMDCF-1.1.3.dist-info/LICENSE
scMDCF-1.1.3.dist-info/METADATA
scMDCF-1.1.3.dist-info/WHEEL
scMDCF-1.1.3.dist-info/top_level.txt
scMDCF-1.1.3.dist-info/RECORD
